shelchemy/__init__.py
shelchemy/cache.py
shelchemy/lazy.py
shelchemy/locker.py
shelchemy/scheduler.py
shelchemy/sqla.py
shelchemy-2.240219.2.dist-info/LICENSE
shelchemy-2.240219.2.dist-info/METADATA
shelchemy-2.240219.2.dist-info/WHEEL
shelchemy-2.240219.2.dist-info/RECORD
