Metadata-Version: 2.1
Name: shelchemy
Version: 2.240219.2
Summary: Shelve-like dict using sqlalchemy as a backend, and lazy scheduler for resuming tasks
License: GPL
Author: davips
Author-email: dpsabc@gmail.com
Requires-Python: >=3.10,<4.0
Classifier: License :: Other/Proprietary License
Classifier: Programming Language :: Python :: 3
Classifier: Programming Language :: Python :: 3.10
Classifier: Programming Language :: Python :: 3.11
Classifier: Programming Language :: Python :: 3.12
Provides-Extra: full
Requires-Dist: SQLAlchemy (>=1.4.39,<2.0.0)
Requires-Dist: lz4 (>=4.0.2,<5.0.0) ; extra == "full"
Requires-Dist: safeserializer (>=0.230202.1,<0.230203.0) ; extra == "full"
Requires-Dist: temporenc (>=0.1.0,<0.2.0)
